harbor_tools/__init__.py
hls/__init__.py
HarborTools-0.0.1.dist-info/METADATA
HarborTools-0.0.1.dist-info/WHEEL
HarborTools-0.0.1.dist-info/top_level.txt
HarborTools-0.0.1.dist-info/RECORD
