Metadata-Version: 2.1
Name: HarborTools
Version: 0.0.1
Summary: HarborTools Package
Author: HarborTools
License: MIT
Classifier: Programming Language :: Python :: 3
Classifier: License :: OSI Approved :: MIT License
Classifier: Operating System :: OS Independent
